pymr/__init__.py
pymr/pymr.py
pymr-2.0.1.dist-info/DESCRIPTION.rst
pymr-2.0.1.dist-info/entry_points.txt
pymr-2.0.1.dist-info/METADATA
pymr-2.0.1.dist-info/metadata.json
pymr-2.0.1.dist-info/RECORD
pymr-2.0.1.dist-info/top_level.txt
pymr-2.0.1.dist-info/WHEEL
