Metadata-Version: 2.0
Name: pymr
Version: 2.0.1
Summary: A tool for executing ANY command in a set of tagged directories.
Home-page: https://github.com/kpurdon/pymr
Author: Kyle W Purdon
Author-email: kylepurdon@gmail.com
License: UNKNOWN
Download-URL: https://github.com/kpurdon/pymr
Platform: UNKNOWN
Classifier: Environment :: Console
Classifier: Operating System :: OS Independent
Classifier: License :: OSI Approved :: GNU General Public License v3 or later (GPLv3+)
Classifier: Intended Audience :: Developers
Classifier: Programming Language :: Python
Classifier: Programming Language :: Python :: 2
Classifier: Programming Language :: Python :: 2.7
Requires-Dist: click (>=4,<5)
